{
  "updatedAt": "2026-02-06T19:57:32.526Z",
  "createdAt": "2026-02-06T17:42:21.849Z",
  "id": "2hN3vxnASq101YawqWKud",
  "name": "Catbook_form_builder",
  "active": false,
  "isArchived": false,
  "nodes": [
    {
      "parameters": {},
      "type": "n8n-nodes-base.manualTrigger",
      "typeVersion": 1,
      "position": [
        0,
        0
      ],
      "id": "4fc5e0ae-926a-4954-9030-b23784c9410e",
      "name": "When clicking ‘Execute workflow’"
    },
    {
      "parameters": {
        "mode": "raw",
        "jsonOutput": "{'items': [\n  {\n    \"username\": \"@AleekKau\",\n    \"entries\": [\n      {\n        \"link\": \"https://t.me/catbookcatebi/4096\",\n        \"header\": \"Пако\",\n        \"posting_date\": \"2025-11-01 10:44:01\"\n      },\n      {\n        \"link\": \"https://t.me/catbookcatebi/4094\",\n        \"header\": \"Бяка\",\n        \"posting_date\": \"2025-10-31 14:51:04\"\n      },\n      {\n        \"link\": \"https://t.me/catbookcatebi/4081\",\n        \"header\": \"😱 Внимание! В Тбилиси Тигр вырвался на свободу!\",\n        \"posting_date\": \"2025-10-30 13:47:02\"\n      },\n      {\n        \"link\": \"https://t.me/catbookcatebi/3185\",\n        \"header\": \"Бяка\",\n        \"posting_date\": \"2025-06-09 07:42:13\"\n      },\n      {\n        \"link\": \"https://t.me/catbookcatebi/2751\",\n        \"header\": \"Барсук\",\n        \"posting_date\": \"2025-03-05 13:55:35\"\n      },\n      {\n        \"link\": \"https://t.me/catbookcatebi/1417\",\n        \"header\": \"Шурале\",\n        \"posting_date\": \"2024-07-19 07:45:42\"\n      }\n    ]\n  },\n  {\n    \"username\": \"@AliqueMagnifique\",\n    \"entries\": [\n      {\n        \"link\": \"https://t.me/catbookcatebi/2997\",\n        \"header\": \"Черепашка Куся\",\n        \"posting_date\": \"2025-05-14 14:26:04\"\n      }\n    ]\n  },\n  {\n    \"username\": \"@Ana_veg_9\",\n    \"entries\": [\n      {\n        \"link\": \"https://t.me/catbookcatebi/1810\",\n        \"header\": \"Саломе\",\n        \"posting_date\": \"2024-09-26 07:19:20\"\n      }\n    ]\n  },\n  {\n    \"username\": \"@BabaLeila\",\n    \"entries\": [\n      {\n        \"link\": \"https://t.me/catbookcatebi/4018\",\n        \"header\": \"Три сладких котёнка ищут дом ✨\",\n        \"posting_date\": \"2025-10-18 17:32:35\"\n      },\n      {\n        \"link\": \"https://t.me/catbookcatebi/1978\",\n        \"header\": \"Соня, Сонёнок, Слонёнок\",\n        \"posting_date\": \"2024-10-21 11:16:08\"\n      }\n    ]\n  },\n  {\n    \"username\": \"@Ekaterina_VE\",\n    \"entries\": [\n      {\n        \"link\": \"https://t.me/catbookcatebi/2985\",\n        \"header\": \"Котята\",\n        \"posting_date\": \"2025-05-10 14:25:56\"\n      }\n    ]\n  },\n  {\n    \"username\": \"@EleneLogacheva\",\n    \"entries\": [\n      {\n        \"link\": \"https://t.me/catbookcatebi/3146\",\n        \"header\": \"Котик без имени ищет семью\",\n        \"posting_date\": \"2025-06-05 09:05:56\"\n      }\n    ]\n  },\n  {\n    \"username\": \"@GalaGe\",\n    \"entries\": [\n      {\n        \"link\": \"https://t.me/catbookcatebi/3485\",\n        \"header\": \"Длинноухая, зеленоглазая красотка Креветочка 🍤\",\n        \"posting_date\": \"2025-07-19 08:51:05\"\n      }\n    ]\n  },\n  {\n    \"username\": \"@Gaviota_och\",\n    \"entries\": [\n      {\n        \"link\": \"https://t.me/catbookcatebi/3221\",\n        \"header\": \"Тучка ☁️\",\n        \"posting_date\": \"2025-06-14 10:47:50\"\n      }\n    ]\n  },\n  {\n    \"username\": \"@GregorNya\",\n    \"entries\": [\n      {\n        \"link\": \"https://t.me/catbookcatebi/2728\",\n        \"header\": \"Минни Маус\",\n        \"posting_date\": \"2025-02-26 10:49:57\"\n      }\n    ]\n  },\n  {\n    \"username\": \"@IaninaL\",\n    \"entries\": [\n      {\n        \"link\": \"https://t.me/catbookcatebi/3367\",\n        \"header\": \"Мисо\",\n        \"posting_date\": \"2025-07-04 19:55:42\"\n      }\n    ]\n  },\n  {\n    \"username\": \"@Jenya_210\",\n    \"entries\": [\n      {\n        \"link\": \"https://t.me/catbookcatebi/3760\",\n        \"header\": \"Очаровательная Гизма — любознательная душа\",\n        \"posting_date\": \"2025-09-01 14:49:32\"\n      },\n      {\n        \"link\": \"https://t.me/catbookcatebi/3732\",\n        \"header\": \"Очаровательная красавица Цуцуня❤️\",\n        \"posting_date\": \"2025-08-26 10:49:12\"\n      }\n    ]\n  },\n  {\n    \"username\": \"@Jgfykn\",\n    \"entries\": [\n      {\n        \"link\": \"https://t.me/catbookcatebi/4005\",\n        \"header\": \"Тето\",\n        \"posting_date\": \"2025-10-09 11:00:24\"\n      }\n    ]\n  },\n  {\n    \"username\": \"@KristiMir\",\n    \"entries\": [\n      {\n        \"link\": \"https://t.me/catbookcatebi/3385\",\n        \"header\": \"Меня зовут Милка, я  милая девочка.\",\n        \"posting_date\": \"2025-07-07 12:08:48\"\n      },\n      {\n        \"link\": \"https://t.me/catbookcatebi/3384\",\n        \"header\": \"Меня зовут Бутусик, я ласковый мурлыка.\",\n        \"posting_date\": \"2025-07-07 12:04:45\"\n      }\n    ]\n  },\n  {\n    \"username\": \"@LaRoseDeTroie\",\n    \"entries\": [\n      {\n        \"link\": \"https://t.me/catbookcatebi/4329\",\n        \"header\": \"Софико\",\n        \"posting_date\": \"2025-12-24 20:01:56\"\n      },\n      {\n        \"link\": \"https://t.me/catbookcatebi/4130\",\n        \"header\": \"Лиза и Ромико (Лексо)\",\n        \"posting_date\": \"2025-11-03 15:38:05\"\n      },\n      {\n        \"link\": \"https://t.me/catbookcatebi/4071\",\n        \"header\": \"Angie (Энжи)\",\n        \"posting_date\": \"2025-10-27 16:34:54\"\n      },\n      {\n        \"link\": \"https://t.me/catbookcatebi/3282\",\n        \"header\": \"Люси\",\n        \"posting_date\": \"2025-06-24 19:10:07\"\n      }\n    ]\n  },\n  {\n    \"username\": \"@MarieBifrost\",\n    \"entries\": [\n      {\n        \"link\": \"https://t.me/catbookcatebi/3785\",\n        \"header\": \"Эчу (Echoo) ищет дом и заботливого хозяина 🥹\",\n        \"posting_date\": \"2025-09-03 17:19:24\"\n      }\n    ]\n  },\n  {\n    \"username\": \"@Marine_Stakhieva\",\n    \"entries\": [\n      {\n        \"link\": \"https://t.me/catbookcatebi/3886\",\n        \"header\": \"Ромби\",\n        \"posting_date\": \"2025-09-15 06:15:09\"\n      }\n    ]\n  },\n  {\n    \"username\": \"@Meggi_bit\",\n    \"entries\": [\n      {\n        \"link\": \"https://t.me/catbookcatebi/4454\",\n        \"header\": \"Толстяк — скромный медведь в поисках семьи\",\n        \"posting_date\": \"2026-02-03 14:58:12\"\n      },\n      {\n        \"link\": \"https://t.me/catbookcatebi/3086\",\n        \"header\": \"Тома, моя любовь\",\n        \"posting_date\": \"2025-05-26 15:18:01\"\n      },\n      {\n        \"link\": \"https://t.me/catbookcatebi/3063\",\n        \"header\": \"Пунтуша\",\n        \"posting_date\": \"2025-05-23 16:33:01\"\n      },\n      {\n        \"link\": \"https://t.me/catbookcatebi/3056\",\n        \"header\": \"Эмми\",\n        \"posting_date\": \"2025-05-22 15:29:01\"\n      },\n      {\n        \"link\": \"https://t.me/catbookcatebi/3048\",\n        \"header\": \"Даниэлла\",\n        \"posting_date\": \"2025-05-21 15:21:00\"\n      }\n    ]\n  },\n  {\n    \"username\": \"@MiNowic\",\n    \"entries\": [\n      {\n        \"link\": \"https://t.me/catbookcatebi/4062\",\n        \"header\": \"Микроба готова сделать вас счастливее своей любовью и потешностью🥰\",\n        \"posting_date\": \"2025-10-25 19:01:34\"\n      }\n    ]\n  },\n  {\n    \"username\": \"@Muschinkina\",\n    \"entries\": [\n      {\n        \"link\": \"https://t.me/catbookcatebi/3004\",\n        \"header\": \"Ищем дом для супер-кошечки!\",\n        \"posting_date\": \"2025-05-15 15:48:41\"\n      }\n    ]\n  },\n  {\n    \"username\": \"@NataGofman\",\n    \"entries\": [\n      {\n        \"link\": \"https://t.me/catbookcatebi/1067\",\n        \"header\": \"Дженифер\",\n        \"posting_date\": \"2024-04-18 18:58:06\"\n      }\n    ]\n  },\n  {\n    \"username\": \"@Ninico_lle\",\n    \"entries\": [\n      {\n        \"link\": \"https://t.me/catbookcatebi/2619\",\n        \"header\": \"Миу\",\n        \"posting_date\": \"2025-01-31 10:19:11\"\n      }\n    ]\n  },\n  {\n    \"username\": \"@NinoMard\",\n    \"entries\": [\n      {\n        \"link\": \"https://t.me/catbookcatebi/3684\",\n        \"header\": \"Малыш Элвис ищет дом\",\n        \"posting_date\": \"2025-08-16 19:24:06\"\n      }\n    ]\n  },\n  {\n    \"username\": \"@NordicKokot\",\n    \"entries\": [\n      {\n        \"link\": \"https://t.me/catbookcatebi/3982\",\n        \"header\": \"Орео\",\n        \"posting_date\": \"2025-10-04 04:33:12\"\n      }\n    ]\n  },\n  {\n    \"username\": \"@Oleg_G_K\",\n    \"entries\": [\n      {\n        \"link\": \"https://t.me/catbookcatebi/1120\",\n        \"header\": \"Такседо\",\n        \"posting_date\": \"2024-05-03 08:32:30\"\n      }\n    ]\n  },\n  {\n    \"username\": \"@Pearline\",\n    \"entries\": [\n      {\n        \"link\": \"https://t.me/catbookcatebi/4338\",\n        \"header\": \"Нежная фройляйн Грета в поисках дома\",\n        \"posting_date\": \"2025-12-27 07:19:54\"\n      },\n      {\n        \"link\": \"https://t.me/catbookcatebi/4324\",\n        \"header\": \"Леди Валиди ищет дом\",\n        \"posting_date\": \"2025-12-22 21:42:48\"\n      },\n      {\n        \"link\": \"https://t.me/catbookcatebi/4319\",\n        \"header\": \"Тильда - маленький лучик света и источник тепла в вашем доме\",\n        \"posting_date\": \"2025-12-22 21:41:12\"\n      },\n      {\n        \"link\": \"https://t.me/catbookcatebi/4304\",\n        \"header\": \"Дружелюбный котик Ирис ищет дом!\",\n        \"posting_date\": \"2025-12-17 21:59:21\"\n      },\n      {\n        \"link\": \"https://t.me/catbookcatebi/4279\",\n        \"header\": \"Фаня - настоящий дракон снаружи, но нежный цветок внутри\",\n        \"posting_date\": \"2025-12-12 05:27:43\"\n      },\n      {\n        \"link\": \"https://t.me/catbookcatebi/4274\",\n        \"header\": \"Очаровательный Доминик ищет дом!\",\n        \"posting_date\": \"2025-12-12 05:25:14\"\n      },\n      {\n        \"link\": \"https://t.me/catbookcatebi/4138\",\n        \"header\": \"Нежный цветочек Ландыш хочет цвести для вас!\",\n        \"posting_date\": \"2025-11-04 02:04:10\"\n      },\n      {\n        \"link\": \"https://t.me/catbookcatebi/4111\",\n        \"header\": \"Очаровательный кот Мамонт ищет своих людей ☺️\",\n        \"posting_date\": \"2025-11-01 20:01:17\"\n      },\n      {\n        \"link\": \"https://t.me/catbookcatebi/4078\",\n        \"header\": \"Финдус\",\n        \"posting_date\": \"2025-10-29 15:06:27\"\n      },\n      {\n        \"link\": \"https://t.me/catbookcatebi/4075\",\n        \"header\": \"Лютик (Пейджер)\",\n        \"posting_date\": \"2025-10-28 17:49:27\"\n      }\n    ]\n  },\n  {\n    \"username\": \"@TeaWithGinger\",\n    \"entries\": [\n      {\n        \"link\": \"https://t.me/catbookcatebi/3777\",\n        \"header\": \"Биба ищет дом!\",\n        \"posting_date\": \"2025-09-03 09:29:54\"\n      }\n    ]\n  },\n  {\n    \"username\": \"@VasDudin\",\n    \"entries\": [\n      {\n        \"link\": \"https://t.me/catbookcatebi/2238\",\n        \"header\": \"Чепа\",\n        \"posting_date\": \"2024-11-22 15:45:37\"\n      }\n    ]\n  },\n  {\n    \"username\": \"@YaggOggaY\",\n    \"entries\": [\n      {\n        \"link\": \"https://t.me/catbookcatebi/4294\",\n        \"header\": \"Лара\",\n        \"posting_date\": \"2025-12-17 17:11:32\"\n      },\n      {\n        \"link\": \"https://t.me/catbookcatebi/3721\",\n        \"header\": \"Лара\",\n        \"posting_date\": \"2025-08-24 06:08:50\"\n      },\n      {\n        \"link\": \"https://t.me/catbookcatebi/3451\",\n        \"header\": \"ДИЛЯ\",\n        \"posting_date\": \"2025-07-15 21:01:32\"\n      },\n      {\n        \"link\": \"https://t.me/catbookcatebi/3445\",\n        \"header\": \"Совенок\",\n        \"posting_date\": \"2025-07-15 20:55:07\"\n      },\n      {\n        \"link\": \"https://t.me/catbookcatebi/3386\",\n        \"header\": \"Котятки-ребятки Малютки, 6-ро котят остались без мамы кошки\",\n        \"posting_date\": \"2025-07-07 12:47:14\"\n      },\n      {\n        \"link\": \"https://t.me/catbookcatebi/3087\",\n        \"header\": \"Пепе\",\n        \"posting_date\": \"2025-05-27 07:25:54\"\n      }\n    ]\n  },\n  {\n    \"username\": \"@aabbcc_1\",\n    \"entries\": [\n      {\n        \"link\": \"https://t.me/catbookcatebi/1164\",\n        \"header\": \"Тиша\",\n        \"posting_date\": \"2024-05-13 08:13:15\"\n      },\n      {\n        \"link\": \"https://t.me/catbookcatebi/1161\",\n        \"header\": \"Буба\",\n        \"posting_date\": \"2024-05-13 08:12:04\"\n      },\n      {\n        \"link\": \"https://t.me/catbookcatebi/1080\",\n        \"header\": \"Тетри\",\n        \"posting_date\": \"2024-04-21 10:07:50\"\n      },\n      {\n        \"link\": \"https://t.me/catbookcatebi/1078\",\n        \"header\": \"Черныш\",\n        \"posting_date\": \"2024-04-21 10:05:49\"\n      },\n      {\n        \"link\": \"https://t.me/catbookcatebi/1060\",\n        \"header\": \"Имбирь\",\n        \"posting_date\": \"2024-04-17 06:22:57\"\n      },\n      {\n        \"link\": \"https://t.me/catbookcatebi/1058\",\n        \"header\": \"Мако\",\n        \"posting_date\": \"2024-04-17 06:21:13\"\n      }\n    ]\n  },\n  {\n    \"username\": \"@aleksakos1\",\n    \"entries\": [\n      {\n        \"link\": \"https://t.me/catbookcatebi/3200\",\n        \"header\": \"Луна\",\n        \"posting_date\": \"2025-06-10 08:54:53\"\n      }\n    ]\n  },\n  {\n    \"username\": \"@alenatrufanov\",\n    \"entries\": [\n      {\n        \"link\": \"https://t.me/catbookcatebi/3110\",\n        \"header\": \"Космос и Рикки\",\n        \"posting_date\": \"2025-05-31 18:22:16\"\n      }\n    ]\n  },\n  {\n    \"username\": \"@alenawlw\",\n    \"entries\": [\n      {\n        \"link\": \"https://t.me/catbookcatebi/3984\",\n        \"header\": \"Дима 👹\",\n        \"posting_date\": \"2025-10-05 17:08:10\"\n      }\n    ]\n  },\n  {\n    \"username\": \"@alevtinavgustova\",\n    \"entries\": [\n      {\n        \"link\": \"https://t.me/catbookcatebi/3679\",\n        \"header\": \"Кошечка\",\n        \"posting_date\": \"2025-08-16 19:21:45\"\n      }\n    ]\n  },\n  {\n    \"username\": \"@alexeevatatyana\",\n    \"entries\": [\n      {\n        \"link\": \"https://t.me/catbookcatebi/4187\",\n        \"header\": \"Котенок-девочка, пока без имени\",\n        \"posting_date\": \"2025-11-13 12:39:51\"\n      },\n      {\n        \"link\": \"https://t.me/catbookcatebi/2577\",\n        \"header\": \"Кошка-котенок, пока\",\n        \"posting_date\": \"2025-01-23 15:04:05\"\n      }\n    ]\n  },\n  {\n    \"username\": \"@allemans\",\n    \"entries\": [\n      {\n        \"link\": \"https://t.me/catbookcatebi/3880\",\n        \"header\": \"Кис\",\n        \"posting_date\": \"2025-09-11 12:05:09\"\n      }\n    ]\n  },\n  {\n    \"username\": \"@anastasiia_kondrakhina\",\n    \"entries\": [\n      {\n        \"link\": \"https://t.me/catbookcatebi/4059\",\n        \"header\": \"Леди-кошка без имени\",\n        \"posting_date\": \"2025-10-23 13:03:09\"\n      },\n      {\n        \"link\": \"https://t.me/catbookcatebi/3997\",\n        \"header\": \"Котята\",\n        \"posting_date\": \"2025-10-08 09:35:44\"\n      }\n    ]\n  },\n  {\n    \"username\": \"@angelina_furman\",\n    \"entries\": [\n      {\n        \"link\": \"https://t.me/catbookcatebi/4102\",\n        \"header\": \"Зеленоглазая принцесса Юми ищет дом\",\n        \"posting_date\": \"2025-11-01 19:57:20\"\n      },\n      {\n        \"link\": \"https://t.me/catbookcatebi/4029\",\n        \"header\": \"😸 Альфа - кошка, которая заставит вас смеяться\",\n        \"posting_date\": \"2025-10-19 16:30:23\"\n      },\n      {\n        \"link\": \"https://t.me/catbookcatebi/3792\",\n        \"header\": \"Юми в поисках дома 🩵\",\n        \"posting_date\": \"2025-09-04 18:15:41\"\n      }\n    ]\n  },\n  {\n    \"username\": \"@angln\",\n    \"entries\": [\n      {\n        \"link\": \"https://t.me/catbookcatebi/3372\",\n        \"header\": \"Кнопка\",\n        \"posting_date\": \"2025-07-05 14:17:35\"\n      }\n    ]\n  },\n  {\n    \"username\": \"@animihi\",\n    \"entries\": [\n      {\n        \"link\": \"https://t.me/catbookcatebi/4333\",\n        \"header\": \"Подросток Чуча\",\n        \"posting_date\": \"2025-12-26 21:49:09\"\n      },\n      {\n        \"link\": \"https://t.me/catbookcatebi/4309\",\n        \"header\": \"Малышка Мышка\",\n        \"posting_date\": \"2025-12-19 20:29:31\"\n      }\n    ]\n  },\n  {\n    \"username\": \"@astro_lina\",\n    \"entries\": [\n      {\n        \"link\": \"https://t.me/catbookcatebi/3862\",\n        \"header\": \"Блоуи\",\n        \"posting_date\": \"2025-09-09 22:25:14\"\n      }\n    ]\n  },\n  {\n    \"username\": \"@bugimenka\",\n    \"entries\": [\n      {\n        \"link\": \"https://t.me/catbookcatebi/3347\",\n        \"header\": \"4 потрясающих котеночка\",\n        \"posting_date\": \"2025-06-27 16:38:59\"\n      }\n    ]\n  },\n  {\n    \"username\": \"@catnomad\",\n    \"entries\": [\n      {\n        \"link\": \"https://t.me/catbookcatebi/2779\",\n        \"header\": \"Лёха ищет любящую семью\",\n        \"posting_date\": \"2025-03-14 09:30:39\"\n      }\n    ]\n  },\n  {\n    \"username\": \"@charlimba\",\n    \"entries\": [\n      {\n        \"link\": \"https://t.me/catbookcatebi/1024\",\n        \"header\": \"Люся\",\n        \"posting_date\": \"2024-03-17 10:20:09\"\n      },\n      {\n        \"link\": \"https://t.me/catbookcatebi/1020\",\n        \"header\": \"Вахушти\",\n        \"posting_date\": \"2024-03-17 10:18:05\"\n      },\n      {\n        \"link\": \"https://t.me/catbookcatebi/1013\",\n        \"header\": \"Тамази\",\n        \"posting_date\": \"2024-03-17 10:13:14\"\n      },\n      {\n        \"link\": \"https://t.me/catbookcatebi/1010\",\n        \"header\": \"Стеша\",\n        \"posting_date\": \"2024-03-17 10:10:39\"\n      },\n      {\n        \"link\": \"https://t.me/catbookcatebi/1000\",\n        \"header\": \"Дуся\",\n        \"posting_date\": \"2024-03-17 10:04:32\"\n      },\n      {\n        \"link\": \"https://t.me/catbookcatebi/997\",\n        \"header\": \"Тина\",\n        \"posting_date\": \"2024-03-17 10:02:03\"\n      },\n      {\n        \"link\": \"https://t.me/catbookcatebi/989\",\n        \"header\": \"Сёма\",\n        \"posting_date\": \"2024-03-17 09:56:58\"\n      }\n    ]\n  },\n  {\n    \"username\": \"@cicutavirosa\",\n    \"entries\": [\n      {\n        \"link\": \"https://t.me/catbookcatebi/2981\",\n        \"header\": \"Кошка Симба ищет дом\",\n        \"posting_date\": \"2025-05-05 15:33:19\"\n      }\n    ]\n  },\n  {\n    \"username\": \"@critskiy\",\n    \"entries\": [\n      {\n        \"link\": \"https://t.me/catbookcatebi/2919\",\n        \"header\": \"Кали\",\n        \"posting_date\": \"2025-04-14 17:17:37\"\n      },\n      {\n        \"link\": \"https://t.me/catbookcatebi/2913\",\n        \"header\": \"Шальная императрица Цицерон\",\n        \"posting_date\": \"2025-04-14 17:15:39\"\n      }\n    ]\n  },\n  {\n    \"username\": \"@d_mamonova\",\n    \"entries\": [\n      {\n        \"link\": \"https://t.me/catbookcatebi/3700\",\n        \"header\": \"Хути, мать-героиня, ищет дом\",\n        \"posting_date\": \"2025-08-20 05:53:51\"\n      },\n      {\n        \"link\": \"https://t.me/catbookcatebi/3659\",\n        \"header\": \"Машка\",\n        \"posting_date\": \"2025-08-13 09:12:06\"\n      },\n      {\n        \"link\": \"https://t.me/catbookcatebi/3654\",\n        \"header\": \"Аватарка\",\n        \"posting_date\": \"2025-08-13 09:09:48\"\n      },\n      {\n        \"link\": \"https://t.me/catbookcatebi/3629\",\n        \"header\": \"Левшиц\",\n        \"posting_date\": \"2025-08-07 13:46:30\"\n      },\n      {\n        \"link\": \"https://t.me/catbookcatebi/3529\",\n        \"header\": \"Юлька\",\n        \"posting_date\": \"2025-07-27 07:11:43\"\n      },\n      {\n        \"link\": \"https://t.me/catbookcatebi/2793\",\n        \"header\": \"Голдор\",\n        \"posting_date\": \"2025-03-17 18:03:16\"\n      }\n    ]\n  },\n  {\n    \"username\": \"@da4ch4nik\",\n    \"entries\": [\n      {\n        \"link\": \"https://t.me/catbookcatebi/4135\",\n        \"header\": \"Маленький чёрный котёнок ищет дом и человека, которому подарит своё мурчащее тепло 🐾\",\n        \"posting_date\": \"2025-11-03 15:41:38\"\n      }\n    ]\n  },\n  {\n    \"username\": \"@dariaartmnv\",\n    \"entries\": [\n      {\n        \"link\": \"https://t.me/catbookcatebi/3189\",\n        \"header\": \"Котята ищут дом🙌🏼\",\n        \"posting_date\": \"2025-06-09 20:03:35\"\n      }\n    ]\n  },\n  {\n    \"username\": \"@dariacoriwoods\",\n    \"entries\": [\n      {\n        \"link\": \"https://t.me/catbookcatebi/3171\",\n        \"header\": \"Бинс\",\n        \"posting_date\": \"2025-06-08 08:52:30\"\n      },\n      {\n        \"link\": \"https://t.me/catbookcatebi/3155\",\n        \"header\": \"Вася\",\n        \"posting_date\": \"2025-06-06 10:57:19\"\n      }\n    ]\n  },\n  {\n    \"username\": \"@dasha_berkut\",\n    \"entries\": [\n      {\n        \"link\": \"https://t.me/catbookcatebi/2375\",\n        \"header\": \"Хатико\",\n        \"posting_date\": \"2024-12-16 13:26:35\"\n      }\n    ]\n  },\n  {\n    \"username\": \"@dddkhhh\",\n    \"entries\": [\n      {\n        \"link\": \"https://t.me/catbookcatebi/3022\",\n        \"header\": \"Кошечка 1565\",\n        \"posting_date\": \"2025-05-20 11:42:25\"\n      },\n      {\n        \"link\": \"https://t.me/catbookcatebi/2649\",\n        \"header\": \"Эльза\",\n        \"posting_date\": \"2025-02-08 15:33:20\"\n      }\n    ]\n  },\n  {\n    \"username\": \"@de_neir\",\n    \"entries\": [\n      {\n        \"link\": \"https://t.me/catbookcatebi/3043\",\n        \"header\": \"Это Рыжик - самый добрый кот\",\n        \"posting_date\": \"2025-05-20 16:53:15\"\n      }\n    ]\n  },\n  {\n    \"username\": \"@egorpes\",\n    \"entries\": [\n      {\n        \"link\": \"https://t.me/catbookcatebi/3713\",\n        \"header\": \"Руби 💎\",\n        \"posting_date\": \"2025-08-22 11:33:26\"\n      },\n      {\n        \"link\": \"https://t.me/catbookcatebi/3473\",\n        \"header\": \"Руби\",\n        \"posting_date\": \"2025-07-17 07:49:16\"\n      }\n    ]\n  },\n  {\n    \"username\": \"@ermacv\",\n    \"entries\": [\n      {\n        \"link\": \"https://t.me/catbookcatebi/4375\",\n        \"header\": \"Познакомьтесь с Беллой. Этой изящная красавица - настоящее чудо!\",\n        \"posting_date\": \"2026-01-08 12:34:31\"\n      },\n      {\n        \"link\": \"https://t.me/catbookcatebi/3810\",\n        \"header\": \"Фрея\",\n        \"posting_date\": \"2025-09-04 18:23:09\"\n      }\n    ]\n  },\n  {\n    \"username\": \"@evgesha11_05\",\n    \"entries\": [\n      {\n        \"link\": \"https://t.me/catbookcatebi/3667\",\n        \"header\": \"МАКС ИЩЕТ ДОМ🏠  🧡 Возраст:\",\n        \"posting_date\": \"2025-08-13 13:27:19\"\n      }\n    ]\n  },\n  {\n    \"username\": \"@fesenkomasha\",\n    \"entries\": [\n      {\n        \"link\": \"https://t.me/catbookcatebi/4284\",\n        \"header\": \"Ищут дом 2 котёнка и их ласковая мама! 🐈🐈🐈\",\n        \"posting_date\": \"2025-12-14 20:20:38\"\n      }\n    ]\n  },\n  {\n    \"username\": \"@idmdaria\",\n    \"entries\": [\n      {\n        \"link\": \"https://t.me/catbookcatebi/3493\",\n        \"header\": \"Малышка Чупа\",\n        \"posting_date\": \"2025-07-20 06:11:28\"\n      }\n    ]\n  },\n  {\n    \"username\": \"@juliasunshiine\",\n    \"entries\": [\n      {\n        \"link\": \"https://t.me/catbookcatebi/3558\",\n        \"header\": \"Молодая кошечка Ксюша с носиком в виде сердечка\",\n        \"posting_date\": \"2025-08-01 16:02:48\"\n      }\n    ]\n  },\n  {\n    \"username\": \"@july_d5\",\n    \"entries\": [\n      {\n        \"link\": \"https://t.me/catbookcatebi/1752\",\n        \"header\": \"Туя\",\n        \"posting_date\": \"2024-09-18 07:02:49\"\n      }\n    ]\n  },\n  {\n    \"username\": \"@julyddd\",\n    \"entries\": [\n      {\n        \"link\": \"https://t.me/catbookcatebi/3143\",\n        \"header\": \"Джеки\",\n        \"posting_date\": \"2025-06-04 10:56:06\"\n      }\n    ]\n  },\n  {\n    \"username\": \"@katya_lazarevav\",\n    \"entries\": [\n      {\n        \"link\": \"https://t.me/catbookcatebi/4123\",\n        \"header\": \"Сабрина маленькая фея в поисках дома ✨\",\n        \"posting_date\": \"2025-11-02 14:15:18\"\n      }\n    ]\n  },\n  {\n    \"username\": \"@kirill25071\",\n    \"entries\": [\n      {\n        \"link\": \"https://t.me/catbookcatebi/3216\",\n        \"header\": \"Заяц\",\n        \"posting_date\": \"2025-06-14 10:39:00\"\n      },\n      {\n        \"link\": \"https://t.me/catbookcatebi/3215\",\n        \"header\": \"Хрюша\",\n        \"posting_date\": \"2025-06-14 10:38:09\"\n      }\n    ]\n  },\n  {\n    \"username\": \"@kkkkkkksssssss\",\n    \"entries\": [\n      {\n        \"link\": \"https://t.me/catbookcatebi/3858\",\n        \"header\": \"Ровена\",\n        \"posting_date\": \"2025-09-09 10:49:40\"\n      },\n      {\n        \"link\": \"https://t.me/catbookcatebi/3855\",\n        \"header\": \"Акула ищет новый дом!\",\n        \"posting_date\": \"2025-09-09 10:49:05\"\n      },\n      {\n        \"link\": \"https://t.me/catbookcatebi/3849\",\n        \"header\": \"Килька\",\n        \"posting_date\": \"2025-09-08 15:02:02\"\n      },\n      {\n        \"link\": \"https://t.me/catbookcatebi/3846\",\n        \"header\": \"Соня\",\n        \"posting_date\": \"2025-09-08 15:01:28\"\n      },\n      {\n        \"link\": \"https://t.me/catbookcatebi/3843\",\n        \"header\": \"Дымок\",\n        \"posting_date\": \"2025-09-08 15:00:41\"\n      },\n      {\n        \"link\": \"https://t.me/catbookcatebi/3827\",\n        \"header\": \"Ириска\",\n        \"posting_date\": \"2025-09-06 07:16:28\"\n      },\n      {\n        \"link\": \"https://t.me/catbookcatebi/3824\",\n        \"header\": \"Персик\",\n        \"posting_date\": \"2025-09-06 07:15:47\"\n      },\n      {\n        \"link\": \"https://t.me/catbookcatebi/3821\",\n        \"header\": \"Абрикос\",\n        \"posting_date\": \"2025-09-06 07:15:07\"\n      }\n    ]\n  },\n  {\n    \"username\": \"@krlv_vtl\",\n    \"entries\": [\n      {\n        \"link\": \"https://t.me/catbookcatebi/4222\",\n        \"header\": \"Расти\",\n        \"posting_date\": \"2025-11-21 14:08:26\"\n      }\n    ]\n  },\n  {\n    \"username\": \"@ksena_vits\",\n    \"entries\": [\n      {\n        \"link\": \"https://t.me/catbookcatebi/3441\",\n        \"header\": \"Кошечка, Буся\",\n        \"posting_date\": \"2025-07-14 20:47:25\"\n      }\n    ]\n  },\n  {\n    \"username\": \"@ksyacid\",\n    \"entries\": [\n      {\n        \"link\": \"https://t.me/catbookcatebi/4396\",\n        \"header\": \"Ричи\",\n        \"posting_date\": \"2026-01-14 08:22:30\"\n      },\n      {\n        \"link\": \"https://t.me/catbookcatebi/4171\",\n        \"header\": \"Сестричка и Братишка (сезон Техникури  УниверсиКоти 2025)\",\n        \"posting_date\": \"2025-11-07 19:38:21\"\n      },\n      {\n        \"link\": \"https://t.me/catbookcatebi/4165\",\n        \"header\": \"▪️Возраст\",\n        \"posting_date\": \"2025-11-06 14:30:40\"\n      },\n      {\n        \"link\": \"https://t.me/catbookcatebi/4158\",\n        \"header\": \"Мисс Форест (сезон Техникури  УниверсиКоти 2025)\",\n        \"posting_date\": \"2025-11-06 11:05:09\"\n      },\n      {\n        \"link\": \"https://t.me/catbookcatebi/3955\",\n        \"header\": \"Дейл\",\n        \"posting_date\": \"2025-10-02 08:59:09\"\n      },\n      {\n        \"link\": \"https://t.me/catbookcatebi/3690\",\n        \"header\": \"Кузя\",\n        \"posting_date\": \"2025-08-18 19:03:40\"\n      },\n      {\n        \"link\": \"https://t.me/catbookcatebi/2730\",\n        \"header\": \"Принцесса\",\n        \"posting_date\": \"2025-02-26 19:13:41\"\n      },\n      {\n        \"link\": \"https://t.me/catbookcatebi/2699\",\n        \"header\": \"Мисфитс\",\n        \"posting_date\": \"2025-02-24 13:41:46\"\n      },\n      {\n        \"link\": \"https://t.me/catbookcatebi/2695\",\n        \"header\": \"Плюшка\",\n        \"posting_date\": \"2025-02-24 13:36:16\"\n      },\n      {\n        \"link\": \"https://t.me/catbookcatebi/2309\",\n        \"header\": \"Варежка (Варя)\",\n        \"posting_date\": \"2024-11-27 08:53:33\"\n      }\n    ]\n  },\n  {\n    \"username\": \"@l_ll_lll_1\",\n    \"entries\": [\n      {\n        \"link\": \"https://t.me/catbookcatebi/3866\",\n        \"header\": \"Готичный\",\n        \"posting_date\": \"2025-09-10 13:32:01\"\n      }\n    ]\n  },\n  {\n    \"username\": \"@lada2211\",\n    \"entries\": [\n      {\n        \"link\": \"https://t.me/catbookcatebi/2388\",\n        \"header\": \"Кроха\",\n        \"posting_date\": \"2024-12-18 16:53:00\"\n      }\n    ]\n  },\n  {\n    \"username\": \"@lanacraft\",\n    \"entries\": [\n      {\n        \"link\": \"https://t.me/catbookcatebi/803\",\n        \"header\": \"Варежка\",\n        \"posting_date\": \"2023-11-17 17:05:09\"\n      }\n    ]\n  },\n  {\n    \"username\": \"@lanagonzo\",\n    \"entries\": [\n      {\n        \"link\": \"https://t.me/catbookcatebi/3067\",\n        \"header\": \"Кава  ▪️Пол:\",\n        \"posting_date\": \"2025-05-24 12:02:00\"\n      }\n    ]\n  },\n  {\n    \"username\": \"@lazzito\",\n    \"entries\": [\n      {\n        \"link\": \"https://t.me/catbookcatebi/3771\",\n        \"header\": \"🤵‍♂️ Мистер Смокинг\",\n        \"posting_date\": \"2025-09-02 17:39:50\"\n      },\n      {\n        \"link\": \"https://t.me/catbookcatebi/3764\",\n        \"header\": \"🐾 Пип-Пип\",\n        \"posting_date\": \"2025-09-02 17:38:26\"\n      }\n    ]\n  },\n  {\n    \"username\": \"@leekrylova\",\n    \"entries\": [\n      {\n        \"link\": \"https://t.me/catbookcatebi/3751\",\n        \"header\": \"Бокси\",\n        \"posting_date\": \"2025-08-31 11:06:05\"\n      }\n    ]\n  },\n  {\n    \"username\": \"@lejafo\",\n    \"entries\": [\n      {\n        \"link\": \"https://t.me/catbookcatebi/1941\",\n        \"header\": \"Зюзя\",\n        \"posting_date\": \"2024-10-16 07:02:54\"\n      }\n    ]\n  },\n  {\n    \"username\": \"@lfhmz\",\n    \"entries\": [\n      {\n        \"link\": \"https://t.me/catbookcatebi/3489\",\n        \"header\": \"Крыса\",\n        \"posting_date\": \"2025-07-19 15:48:23\"\n      },\n      {\n        \"link\": \"https://t.me/catbookcatebi/3296\",\n        \"header\": \"Угроза/Крыса\",\n        \"posting_date\": \"2025-06-26 12:54:35\"\n      }\n    ]\n  },\n  {\n    \"username\": \"@linedolobuga\",\n    \"entries\": [\n      {\n        \"link\": \"https://t.me/catbookcatebi/3602\",\n        \"header\": \"Блошка\",\n        \"posting_date\": \"2025-08-04 18:13:54\"\n      }\n    ]\n  },\n  {\n    \"username\": \"@liubakotorobay\",\n    \"entries\": [\n      {\n        \"link\": \"https://t.me/catbookcatebi/3503\",\n        \"header\": \"Гого\",\n        \"posting_date\": \"2025-07-25 10:50:18\"\n      }\n    ]\n  },\n  {\n    \"username\": \"@lubitel_zefira\",\n    \"entries\": [\n      {\n        \"link\": \"https://t.me/catbookcatebi/3646\",\n        \"header\": \"Кошечка, Сэм\",\n        \"posting_date\": \"2025-08-10 20:22:07\"\n      },\n      {\n        \"link\": \"https://t.me/catbookcatebi/3438\",\n        \"header\": \"Кошечка, Вэнди\",\n        \"posting_date\": \"2025-07-14 06:31:51\"\n      },\n      {\n        \"link\": \"https://t.me/catbookcatebi/3435\",\n        \"header\": \"Котик, Диппер\",\n        \"posting_date\": \"2025-07-14 06:30:52\"\n      },\n      {\n        \"link\": \"https://t.me/catbookcatebi/3405\",\n        \"header\": \"Котик, Зус\",\n        \"posting_date\": \"2025-07-07 19:58:27\"\n      },\n      {\n        \"link\": \"https://t.me/catbookcatebi/3402\",\n        \"header\": \"Кошечка, Сэм\",\n        \"posting_date\": \"2025-07-07 15:01:35\"\n      },\n      {\n        \"link\": \"https://t.me/catbookcatebi/3229\",\n        \"header\": \"Кестанаа\",\n        \"posting_date\": \"2025-06-16 16:38:26\"\n      }\n    ]\n  },\n  {\n    \"username\": \"@matilda01\",\n    \"entries\": [\n      {\n        \"link\": \"https://t.me/catbookcatebi/2542\",\n        \"header\": \"Сэм (Сэмуэль)\",\n        \"posting_date\": \"2025-01-13 18:21:46\"\n      }\n    ]\n  },\n  {\n    \"username\": \"@moore_errors\",\n    \"entries\": [\n      {\n        \"link\": \"https://t.me/catbookcatebi/1095\",\n        \"header\": \"Чучундрик\",\n        \"posting_date\": \"2024-04-23 19:36:14\"\n      }\n    ]\n  },\n  {\n    \"username\": \"@nanikosher\",\n    \"entries\": [\n      {\n        \"link\": \"https://t.me/catbookcatebi/3245\",\n        \"header\": \"Матрешка\",\n        \"posting_date\": \"2025-06-16 19:20:12\"\n      }\n    ]\n  },\n  {\n    \"username\": \"@nastsoy\",\n    \"entries\": [\n      {\n        \"link\": \"https://t.me/catbookcatebi/3574\",\n        \"header\": \"Сокс\",\n        \"posting_date\": \"2025-08-02 13:05:00\"\n      },\n      {\n        \"link\": \"https://t.me/catbookcatebi/3544\",\n        \"header\": \"Депутат в мини-формате\",\n        \"posting_date\": \"2025-07-31 12:47:13\"\n      }\n    ]\n  },\n  {\n    \"username\": \"@nataly140268\",\n    \"entries\": [\n      {\n        \"link\": \"https://t.me/catbookcatebi/3224\",\n        \"header\": \"Муся\",\n        \"posting_date\": \"2025-06-16 12:04:12\"\n      }\n    ]\n  },\n  {\n    \"username\": \"@nktumpv\",\n    \"entries\": [\n      {\n        \"link\": \"https://t.me/catbookcatebi/2894\",\n        \"header\": \"Федя Белоус\",\n        \"posting_date\": \"2025-04-14 11:40:58\"\n      }\n    ]\n  },\n  {\n    \"username\": \"@novodsign\",\n    \"entries\": [\n      {\n        \"link\": \"https://t.me/catbookcatebi/2472\",\n        \"header\": \"Бетти\",\n        \"posting_date\": \"2024-12-29 09:55:12\"\n      }\n    ]\n  },\n  {\n    \"username\": \"@ntragel\",\n    \"entries\": [\n      {\n        \"link\": \"https://t.me/catbookcatebi/4116\",\n        \"header\": \"Куки\",\n        \"posting_date\": \"2025-11-01 20:05:33\"\n      }\n    ]\n  },\n  {\n    \"username\": \"@nuishtoteper\",\n    \"entries\": [\n      {\n        \"link\": \"https://t.me/catbookcatebi/3239\",\n        \"header\": \"Тотоша ищет дом 💕\",\n        \"posting_date\": \"2025-06-16 19:08:08\"\n      }\n    ]\n  },\n  {\n    \"username\": \"@oekuzina\",\n    \"entries\": [\n      {\n        \"link\": \"https://t.me/catbookcatebi/4213\",\n        \"header\": \"Черный котенок ищет дом\",\n        \"posting_date\": \"2025-11-21 13:50:43\"\n      }\n    ]\n  },\n  {\n    \"username\": \"@oison\",\n    \"entries\": [\n      {\n        \"link\": \"https://t.me/catbookcatebi/4034\",\n        \"header\": \"Бьёрн\",\n        \"posting_date\": \"2025-10-20 08:33:17\"\n      },\n      {\n        \"link\": \"https://t.me/catbookcatebi/4001\",\n        \"header\": \"красавица Жемчужинка\",\n        \"posting_date\": \"2025-10-09 08:04:01\"\n      }\n    ]\n  },\n  {\n    \"username\": \"@oks074\",\n    \"entries\": [\n      {\n        \"link\": \"https://t.me/catbookcatebi/1033\",\n        \"header\": \"Пушистик\",\n        \"posting_date\": \"2024-04-09 07:57:44\"\n      }\n    ]\n  },\n  {\n    \"username\": \"@olgaolgina1\",\n    \"entries\": [\n      {\n        \"link\": \"https://t.me/catbookcatebi/1728\",\n        \"header\": \"Звездочка, Багира, Наполеон и мама Даша\",\n        \"posting_date\": \"2024-09-16 11:21:39\"\n      }\n    ]\n  },\n  {\n    \"username\": \"@olia443\",\n    \"entries\": [\n      {\n        \"link\": \"https://t.me/catbookcatebi/4476\",\n        \"header\": \"Белла - маленькая кошка, которая умеет делать людей счастливыми 🤍\",\n        \"posting_date\": \"2026-02-06 14:05:52\"\n      },\n      {\n        \"link\": \"https://t.me/catbookcatebi/4348\",\n        \"header\": \"Песец\",\n        \"posting_date\": \"2025-12-27 13:20:12\"\n      },\n      {\n        \"link\": \"https://t.me/catbookcatebi/3706\",\n        \"header\": \"Кошечка Юкки\",\n        \"posting_date\": \"2025-08-22 11:28:35\"\n      },\n      {\n        \"link\": \"https://t.me/catbookcatebi/3179\",\n        \"header\": \"Виолетта\",\n        \"posting_date\": \"2025-06-08 19:00:35\"\n      },\n      {\n        \"link\": \"https://t.me/catbookcatebi/2958\",\n        \"header\": \"Котик Васенька ищет дом 🙋🏻\",\n        \"posting_date\": \"2025-04-24 18:16:13\"\n      },\n      {\n        \"link\": \"https://t.me/catbookcatebi/2954\",\n        \"header\": \"Кошечка Шуня ищет дом 💫\",\n        \"posting_date\": \"2025-04-24 18:12:39\"\n      }\n    ]\n  },\n  {\n    \"username\": \"@orbiresidence\",\n    \"entries\": [\n      {\n        \"link\": \"https://t.me/catbookcatebi/4263\",\n        \"header\": \"Котики Магги и Гарри\",\n        \"posting_date\": \"2025-12-09 13:20:51\"\n      }\n    ]\n  },\n  {\n    \"username\": \"@radiantheat\",\n    \"entries\": [\n      {\n        \"link\": \"https://t.me/catbookcatebi/4466\",\n        \"header\": \"Братик и сестрёнка с Пекини\",\n        \"posting_date\": \"2026-02-06 11:43:03\"\n      },\n      {\n        \"link\": \"https://t.me/catbookcatebi/4433\",\n        \"header\": \"Муши-смешные уши ищет дом.\",\n        \"posting_date\": \"2026-01-30 09:16:11\"\n      },\n      {\n        \"link\": \"https://t.me/catbookcatebi/4428\",\n        \"header\": \"Братик и сестрёнка с Пекини (зову их пока Рыжик и Цветик, имена пусть выберут хозяева).\",\n        \"posting_date\": \"2026-01-19 16:51:05\"\n      },\n      {\n        \"link\": \"https://t.me/catbookcatebi/4381\",\n        \"header\": \"Муши-смешные уши ищет дом.\",\n        \"posting_date\": \"2026-01-10 10:25:58\"\n      }\n    ]\n  },\n  {\n    \"username\": \"@rerion_eyes\",\n    \"entries\": [\n      {\n        \"link\": \"https://t.me/catbookcatebi/3408\",\n        \"header\": \"Бычок - большой, плюшевый и очень нежный кот!\",\n        \"posting_date\": \"2025-07-08 12:50:29\"\n      },\n      {\n        \"link\": \"https://t.me/catbookcatebi/2708\",\n        \"header\": \"Алекс — огненный красавец, любопытный и открытый этому миру!\",\n        \"posting_date\": \"2025-02-24 18:31:05\"\n      }\n    ]\n  },\n  {\n    \"username\": \"@salem_dreamin\",\n    \"entries\": [\n      {\n        \"link\": \"https://t.me/catbookcatebi/2507\",\n        \"header\": \"Нежный мальчик Чука\",\n        \"posting_date\": \"2025-01-07 16:43:40\"\n      }\n    ]\n  },\n  {\n    \"username\": \"@sergeydmitriev\",\n    \"entries\": [\n      {\n        \"link\": \"https://t.me/catbookcatebi/3161\",\n        \"header\": \"Щепка\",\n        \"posting_date\": \"2025-06-06 11:30:18\"\n      }\n    ]\n  },\n  {\n    \"username\": \"@stacy_orl\",\n    \"entries\": [\n      {\n        \"link\": \"https://t.me/catbookcatebi/3991\",\n        \"header\": \"Красавица Грейси ищет дом.\",\n        \"posting_date\": \"2025-10-08 07:44:12\"\n      }\n    ]\n  },\n  {\n    \"username\": \"@svesjnpb\",\n    \"entries\": [\n      {\n        \"link\": \"https://t.me/catbookcatebi/4358\",\n        \"header\": \"Я самый обычный котенок по-твоему!?\",\n        \"posting_date\": \"2025-12-28 15:08:24\"\n      },\n      {\n        \"link\": \"https://t.me/catbookcatebi/4176\",\n        \"header\": \"Я самый обычный котенок по-твоему!?\",\n        \"posting_date\": \"2025-11-08 19:03:37\"\n      },\n      {\n        \"link\": \"https://t.me/catbookcatebi/3964\",\n        \"header\": \"Малифисента из зачарованного леса ищет дом\",\n        \"posting_date\": \"2025-10-02 14:42:11\"\n      },\n      {\n        \"link\": \"https://t.me/catbookcatebi/3593\",\n        \"header\": \"Супершерстяной котенок Хепри\",\n        \"posting_date\": \"2025-08-04 07:00:39\"\n      }\n    ]\n  },\n  {\n    \"username\": \"@taisianaa\",\n    \"entries\": [\n      {\n        \"link\": \"https://t.me/catbookcatebi/2716\",\n        \"header\": \"Мелисса\",\n        \"posting_date\": \"2025-02-25 08:07:14\"\n      }\n    ]\n  },\n  {\n    \"username\": \"@tatiana_pie\",\n    \"entries\": [\n      {\n        \"link\": \"https://t.me/catbookcatebi/3381\",\n        \"header\": \"Две сестры: Котарина и Макрошка\",\n        \"posting_date\": \"2025-07-05 17:54:33\"\n      }\n    ]\n  },\n  {\n    \"username\": \"@tenktesla\",\n    \"entries\": [\n      {\n        \"link\": \"https://t.me/catbookcatebi/3509\",\n        \"header\": \"Малыш Пиксель 🐱\",\n        \"posting_date\": \"2025-07-25 11:19:02\"\n      }\n    ]\n  },\n  {\n    \"username\": \"@teytsurkava\",\n    \"entries\": [\n      {\n        \"link\": \"https://t.me/catbookcatebi/3333\",\n        \"header\": \"Рам\",\n        \"posting_date\": \"2025-06-27 07:16:13\"\n      },\n      {\n        \"link\": \"https://t.me/catbookcatebi/3325\",\n        \"header\": \"Сван\",\n        \"posting_date\": \"2025-06-27 07:06:40\"\n      },\n      {\n        \"link\": \"https://t.me/catbookcatebi/3317\",\n        \"header\": \"Мими - Мимо\",\n        \"posting_date\": \"2025-06-27 07:02:14\"\n      },\n      {\n        \"link\": \"https://t.me/catbookcatebi/3308\",\n        \"header\": \"Ника\",\n        \"posting_date\": \"2025-06-27 06:58:16\"\n      },\n      {\n        \"link\": \"https://t.me/catbookcatebi/3300\",\n        \"header\": \"Кари\",\n        \"posting_date\": \"2025-06-26 13:05:39\"\n      },\n      {\n        \"link\": \"https://t.me/catbookcatebi/3288\",\n        \"header\": \"Хари\",\n        \"posting_date\": \"2025-06-25 11:21:28\"\n      }\n    ]\n  },\n  {\n    \"username\": \"@thekateryna\",\n    \"entries\": [\n      {\n        \"link\": \"https://t.me/catbookcatebi/2868\",\n        \"header\": \"Ласкуша Катя\",\n        \"posting_date\": \"2025-04-07 13:38:04\"\n      }\n    ]\n  },\n  {\n    \"username\": \"@tischa13\",\n    \"entries\": [\n      {\n        \"link\": \"https://t.me/catbookcatebi/4460\",\n        \"header\": \"Шкварка — самая любвеобильная кошка в мире!\",\n        \"posting_date\": \"2026-02-04 04:30:59\"\n      },\n      {\n        \"link\": \"https://t.me/catbookcatebi/4448\",\n        \"header\": \"Медок - нежная зазноба вашего сердца\",\n        \"posting_date\": \"2026-02-03 06:26:56\"\n      },\n      {\n        \"link\": \"https://t.me/catbookcatebi/4442\",\n        \"header\": \"Кошка Техничка — для сильных духом!\",\n        \"posting_date\": \"2026-02-03 06:20:10\"\n      },\n      {\n        \"link\": \"https://t.me/catbookcatebi/4257\",\n        \"header\": \"Хотите попробовать настоящую магию? Берите Мару! ✨\",\n        \"posting_date\": \"2025-11-30 20:28:32\"\n      }\n    ]\n  },\n  {\n    \"username\": \"@tlent1\",\n    \"entries\": [\n      {\n        \"link\": \"https://t.me/catbookcatebi/3898\",\n        \"header\": \"Кошечка Пива\",\n        \"posting_date\": \"2025-09-17 11:38:35\"\n      }\n    ]\n  },\n  {\n    \"username\": \"@tomateit\",\n    \"entries\": [\n      {\n        \"link\": \"https://t.me/catbookcatebi/3498\",\n        \"header\": \"Котята из фонтана\",\n        \"posting_date\": \"2025-07-23 06:36:24\"\n      }\n    ]\n  },\n  {\n    \"username\": \"@veronaveronovna\",\n    \"entries\": [\n      {\n        \"link\": \"https://t.me/catbookcatebi/3217\",\n        \"header\": \"КОТЯТА\",\n        \"posting_date\": \"2025-06-14 10:43:57\"\n      }\n    ]\n  },\n  {\n    \"username\": \"@vitasiempre\",\n    \"entries\": [\n      {\n        \"link\": \"https://t.me/catbookcatebi/3674\",\n        \"header\": \"Бусинка\",\n        \"posting_date\": \"2025-08-15 08:49:38\"\n      }\n    ]\n  },\n  {\n    \"username\": \"@yaaaaden\",\n    \"entries\": [\n      {\n        \"link\": \"https://t.me/catbookcatebi/3869\",\n        \"header\": \"Листик / Иви / Виви\",\n        \"posting_date\": \"2025-09-11 11:55:30\"\n      }\n    ]\n  },\n  {\n    \"username\": \"@yana_kushchenko\",\n    \"entries\": [\n      {\n        \"link\": \"https://t.me/catbookcatebi/3455\",\n        \"header\": \"Котёнок-девочка\",\n        \"posting_date\": \"2025-07-15 21:04:21\"\n      }\n    ]\n  }\n]}",
        "options": {}
      },
      "type": "n8n-nodes-base.set",
      "typeVersion": 3.4,
      "position": [
        208,
        0
      ],
      "id": "1dfacf4b-667e-4ad1-97a6-ce0a4ca0cba4",
      "name": "Edit Fields"
    },
    {
      "parameters": {
        "fieldToSplitOut": "items",
        "include": "allOtherFields",
        "options": {}
      },
      "type": "n8n-nodes-base.splitOut",
      "typeVersion": 1,
      "position": [
        416,
        0
      ],
      "id": "9cf9c52a-b869-4512-9f41-f619f7198630",
      "name": "Split Out"
    },
    {
      "parameters": {
        "mode": "runOnceForEachItem",
        "language": "pythonNative",
        "pythonCode": "import uuid\n\ndef u():\n    return str(uuid.uuid4())\n\ndef html_schema(text: str):\n    return [[text]]\n\ndef build_ad_section(ad_index: int, ad: dict):\n    blocks = []\n\n    # Section heading\n    blocks.append({\n        \"uuid\": u(),\n        \"type\": \"HEADING_2\",\n        \"groupUuid\": u(),\n        \"groupType\": \"HEADING_2\",\n        \"payload\": {\"safeHTMLSchema\": html_schema(f\"Объявление #{ad_index + 1}\")}\n    })\n\n    # Ad context\n    header = ad.get(\"header\", f\"Объявление #{ad_index + 1}\")\n    link = ad.get(\"link\", \"\")\n    posting_date = ad.get(\"posting_date\", \"\")\n\n    lines = [f\"<b>{header}</b>\"]\n    if posting_date:\n        lines.append(f\"Дата: {posting_date}\")\n    if link:\n        lines.append(f\"Ссылка: {link}\")\n\n    blocks.append({\n        \"uuid\": u(),\n        \"type\": \"TEXT\",\n        \"groupUuid\": u(),\n        \"groupType\": \"TEXT\",\n        \"payload\": {\"safeHTMLSchema\": html_schema(\"<br>\".join(lines))}\n    })\n\n    # Q1\n    mc_group = u()\n\n    blocks.append({\n        \"uuid\": u(),\n        \"type\": \"TITLE\",\n        \"groupUuid\": u(),\n        \"groupType\": \"QUESTION\",\n        \"payload\": {\n            \"isFolded\": False,\n            \"safeHTMLSchema\": html_schema(\"Актуально ли объявление?\")\n        }\n    })\n\n    opt_yes_uuid = u()\n    opt_no_uuid = u()\n    opt_other_uuid = u()\n\n    blocks.append({\n        \"uuid\": opt_yes_uuid,\n        \"type\": \"MULTIPLE_CHOICE_OPTION\",\n        \"groupUuid\": mc_group,\n        \"groupType\": \"MULTIPLE_CHOICE\",\n        \"payload\": {\n            \"index\": 0, \"isRequired\": True, \"isFirst\": True, \"isLast\": False,\n            \"hasOtherOption\": True, \"text\": \"Объявление актуально\"\n        }\n    })\n\n    blocks.append({\n        \"uuid\": opt_no_uuid,\n        \"type\": \"MULTIPLE_CHOICE_OPTION\",\n        \"groupUuid\": mc_group,\n        \"groupType\": \"MULTIPLE_CHOICE\",\n        \"payload\": {\n            \"index\": 1, \"isRequired\": True, \"isFirst\": False, \"isLast\": False,\n            \"hasOtherOption\": True, \"text\": \"Объявление не актуально\"\n        }\n    })\n\n    blocks.append({\n        \"uuid\": opt_other_uuid,\n        \"type\": \"MULTIPLE_CHOICE_OPTION\",\n        \"groupUuid\": mc_group,\n        \"groupType\": \"MULTIPLE_CHOICE\",\n        \"payload\": {\n            \"isOtherOption\": True, \"index\": 2, \"isRequired\": True,\n            \"isFirst\": False, \"isLast\": True, \"hasOtherOption\": True, \"text\": \"Other\"\n        }\n    })\n\n    # Q2 (hidden)\n    q2_title_uuid = u()\n    q2_mc_group = u()\n\n    blocks.append({\n        \"uuid\": q2_title_uuid,\n        \"type\": \"TITLE\",\n        \"groupUuid\": u(),\n        \"groupType\": \"QUESTION\",\n        \"payload\": {\n            \"isFolded\": False,\n            \"isHidden\": True,\n            \"safeHTMLSchema\": html_schema(\"Что случилось с животным?\")\n        }\n    })\n\n    follow_opts = [\n        \"Пристроили\",\n        \"Оставили себе\",\n        \"Умерло\",\n        \"Проходит лечение / адаптацию\",\n        \"Выпустили на улицу\",\n    ]\n\n    follow_opt_uuids = []\n    for i, t in enumerate(follow_opts):\n        ou = u()\n        follow_opt_uuids.append(ou)\n        blocks.append({\n            \"uuid\": ou,\n            \"type\": \"MULTIPLE_CHOICE_OPTION\",\n            \"groupUuid\": q2_mc_group,\n            \"groupType\": \"MULTIPLE_CHOICE\",\n            \"payload\": {\n                \"index\": i, \"isRequired\": True, \"isFirst\": (i == 0), \"isLast\": False,\n                \"hasOtherOption\": True, \"isHidden\": True, \"text\": t\n            }\n        })\n\n    follow_other_uuid = u()\n    blocks.append({\n        \"uuid\": follow_other_uuid,\n        \"type\": \"MULTIPLE_CHOICE_OPTION\",\n        \"groupUuid\": q2_mc_group,\n        \"groupType\": \"MULTIPLE_CHOICE\",\n        \"payload\": {\n            \"isOtherOption\": True, \"index\": len(follow_opts), \"isRequired\": True,\n            \"isFirst\": False, \"isLast\": True, \"hasOtherOption\": True,\n            \"isHidden\": True, \"text\": \"Other\"\n        }\n    })\n\n    # Conditional logic: if Q1 == \"not актуально\" => show Q2 blocks\n    show_blocks = [q2_title_uuid] + follow_opt_uuids + [follow_other_uuid]\n\n    blocks.append({\n        \"uuid\": u(),\n        \"type\": \"CONDITIONAL_LOGIC\",\n        \"groupUuid\": u(),\n        \"groupType\": \"CONDITIONAL_LOGIC\",\n        \"payload\": {\n            \"updateUuid\": u(),\n            \"logicalOperator\": \"AND\",\n            \"conditionals\": [\n                {\n                    \"uuid\": u(),\n                    \"type\": \"SINGLE\",\n                    \"payload\": {\n                        \"field\": {\n                            \"uuid\": mc_group,\n                            \"type\": \"INPUT_FIELD\",\n                            \"questionType\": \"MULTIPLE_CHOICE\",\n                            \"blockGroupUuid\": mc_group,\n                            \"title\": \"Актуально ли объявление?\"\n                        },\n                        \"comparison\": \"IS\",\n                        \"value\": opt_no_uuid\n                    }\n                }\n            ],\n            \"actions\": [\n                {\n                    \"uuid\": u(),\n                    \"type\": \"SHOW_BLOCKS\",\n                    \"payload\": {\"showBlocks\": show_blocks}\n                }\n            ]\n        }\n    })\n\n    return blocks\n\n\n# -------- native python input --------\ndata = _item['json']['items']\n\nusername = data['username']\nads = data['entries']\n\nblocks = []\n\nblocks.append({\n    \"uuid\": u(),\n    \"type\": \"FORM_TITLE\",\n    \"groupUuid\": u(),\n    \"groupType\": \"TEXT\",\n    \"payload\": {\n        \"button\": {\"label\": \"Отправить ответы\"},\n        \"safeHTMLSchema\": html_schema(f\"Форма для {username}\"),\n        \"title\": f\"Форма для {username}\"\n    }\n})\n\nblocks.append({\n    \"uuid\": u(),\n    \"type\": \"TEXT\",\n    \"groupUuid\": u(),\n    \"groupType\": \"TEXT\",\n    \"payload\": {\n        \"safeHTMLSchema\": html_schema(\n            f\"В Catbook сейчас есть {len(ads)} ваших объявлений, давайте поймём, какие актуальны.\"\n        )\n    }\n})\n\nfor i, ad in enumerate(ads):\n    blocks.extend(build_ad_section(i, ad))\n\npayload = {\n    \"status\": \"PUBLISHED\",\n    \"settings\": {\n        \"language\": \"en\",\n        \"hasProgressBar\": True,\n        \"saveForLater\": True,\n        \"pageAutoJump\": False\n    },\n    \"blocks\": blocks\n}\n\n# IMPORTANT: native python expects list of dicts (each dict is item.json)\nreturn {'result':payload}\n"
      },
      "type": "n8n-nodes-base.code",
      "typeVersion": 2,
      "position": [
        624,
        0
      ],
      "id": "c75c242c-ff52-4a9f-99f1-7645d910614a",
      "name": "Code in Python"
    },
    {
      "parameters": {
        "method": "POST",
        "url": "https://api.tally.so/forms",
        "authentication": "predefinedCredentialType",
        "nodeCredentialType": "httpBearerAuth",
        "sendBody": true,
        "specifyBody": "json",
        "jsonBody": "={{ $json.result }}",
        "options": {
          "batching": {
            "batch": {
              "batchSize": 1
            }
          }
        }
      },
      "type": "n8n-nodes-base.httpRequest",
      "typeVersion": 4.4,
      "position": [
        832,
        0
      ],
      "id": "90c74e2f-6242-4b8d-931b-d1b393994475",
      "name": "HTTP Request",
      "credentials": {
        "httpBearerAuth": {
          "id": "8YxdqvcEIK7SBTPa",
          "name": "Tally"
        }
      }
    }
  ],
  "connections": {
    "When clicking ‘Execute workflow’": {
      "main": [
        [
          {
            "node": "Edit Fields",
            "type": "main",
            "index": 0
          }
        ]
      ]
    },
    "Edit Fields": {
      "main": [
        [
          {
            "node": "Split Out",
            "type": "main",
            "index": 0
          }
        ]
      ]
    },
    "Split Out": {
      "main": [
        [
          {
            "node": "Code in Python",
            "type": "main",
            "index": 0
          }
        ]
      ]
    },
    "Code in Python": {
      "main": [
        [
          {
            "node": "HTTP Request",
            "type": "main",
            "index": 0
          }
        ]
      ]
    }
  },
  "settings": {
    "executionOrder": "v1",
    "binaryMode": "separate",
    "availableInMCP": false
  },
  "staticData": null,
  "meta": null,
  "pinData": {},
  "versionId": "8ddaf0b6-34bd-496d-a14d-b8c142641f75",
  "activeVersionId": null,
  "triggerCount": 0,
  "shared": [
    {
      "updatedAt": "2026-02-06T17:42:21.859Z",
      "createdAt": "2026-02-06T17:42:21.859Z",
      "role": "workflow:owner",
      "workflowId": "2hN3vxnASq101YawqWKud",
      "projectId": "jnu5GnxkoXUPZEif"
    }
  ],
  "activeVersion": null,
  "tags": []
}